yeastr/as_decorator.py
yeastr/as_decorators.pyy
yeastr/backport_dict_ops.pyy
yeastr/backport_fstring_backslash.pyy
yeastr/backport_match.pyy
yeastr/bootstrapped.py
yeastr/build_time_transformer.pyy
yeastr/impl_call2comp.pyy
yeastr/impl_macros.pyy
yeastr/impl_namedloops.pyy
yeastr/import_hooks.py
yeastr/import_hooks.pyy
yeastr/interactive.py
yeastr/minimal_runtime.py
yeastr/packaging_test.py
yeastr/packaging_test.pyy
yeastr/py39unparser.py
yeastr/shared.ypy
yeastr/stabilize_ast_for_ci.py
yeastr/utils.py
yeastr/yam.ypy
yeastr-0.0.2.dist-info/licenses/LICENSE
yeastr-0.0.2.dist-info/METADATA
yeastr-0.0.2.dist-info/WHEEL
yeastr-0.0.2.dist-info/top_level.txt
yeastr-0.0.2.dist-info/RECORD
