Metadata-Version: 2.4
Name: yeastr
Version: 0.0.2
Summary: Syntactical Sugar Transformations
Author-email: Castiglia Vincenzo <castix@autistici.org>
License-Expression: PSF-2.0
Project-URL: Homepage, https://github.com/yeastr-org/yeastr
Project-URL: Issues, https://github.com/yeastr-org/yeastr/issues
Classifier: Programming Language :: Python :: 3
Classifier: Operating System :: OS Independent
Classifier: Development Status :: 3 - Alpha
Classifier: Intended Audience :: Developers
Classifier: Intended Audience :: System Administrators
Classifier: Intended Audience :: Telecommunications Industry
Classifier: Topic :: Software Development
Classifier: Programming Language :: Python :: 3.8
Classifier: Programming Language :: Python :: 3.9
Classifier: Programming Language :: Python :: 3.10
Classifier: Programming Language :: Python :: 3.11
Classifier: Programming Language :: Python :: 3.12
Classifier: Programming Language :: Python :: 3.13
Classifier: Programming Language :: Python :: 3.14
Requires-Python: >=3.8
License-File: LICENSE
Dynamic: classifier
Dynamic: license-file
